uwqsc_backtesting_framework/__init__.py
uwqsc_backtesting_framework/conv_to_parquet.py
uwqsc_backtesting_framework/main.py
uwqsc_backtesting_framework/interfaces/IBacktestingFramework.py
uwqsc_backtesting_framework/interfaces/__init__.py
uwqsc_backtesting_framework-2025.3.7.dist-info/LICENSE
uwqsc_backtesting_framework-2025.3.7.dist-info/METADATA
uwqsc_backtesting_framework-2025.3.7.dist-info/WHEEL
uwqsc_backtesting_framework-2025.3.7.dist-info/top_level.txt
uwqsc_backtesting_framework-2025.3.7.dist-info/RECORD
