Metadata-Version: 2.2
Name: uwqsc-backtesting-framework
Version: 2025.3.7
Summary: The University of Waterloo quantitative analysis stocks club backtesting framework repository.
Author-email: Sargun Singh Bhatti <sargunbhatti27@gmail.com>, Param Shah <paramshah07@gmail.com>, Raghav Bhasin <raghav9909@gmail.com>
Project-URL: Homepage, https://github.com/UWQSC/backtesting-framework
Classifier: Programming Language :: Python :: 3
Classifier: Operating System :: OS Independent
Classifier: License :: OSI Approved :: MIT License
Requires-Python: >=3.9
License-File: LICENSE
Requires-Dist: streamlit==1.43.0
Requires-Dist: uwqsc-algorithmic-trading==2025.3.7.post2
